django_messages_drf/__init__.py
django_messages_drf/admin.py
django_messages_drf/apps.py
django_messages_drf/mixins.py
django_messages_drf/models.py
django_messages_drf/pagination.py
django_messages_drf/permissions.py
django_messages_drf/serializers.py
django_messages_drf/settings.py
django_messages_drf/signals.py
django_messages_drf/urls.py
django_messages_drf/utils.py
django_messages_drf/views.py
django_messages_drf/migrations/0001_initial.py
django_messages_drf/migrations/__init__.py
django_messages_drf/tests/__init__.py
django_messages_drf/tests/factories.py
django_messages_drf/tests/test_cases.py
django_messages_drf/tests/test_models.py
django_messages_drf/tests/test_settings.py
django_messages_drf/tests/test_views.py
django_messages_drf/tests/urls.py
django_messages_drf/tests/utils.py
django_messages_drf-1.0.6.dist-info/AUTHORS
django_messages_drf-1.0.6.dist-info/LICENSE
django_messages_drf-1.0.6.dist-info/METADATA
django_messages_drf-1.0.6.dist-info/WHEEL
django_messages_drf-1.0.6.dist-info/top_level.txt
django_messages_drf-1.0.6.dist-info/RECORD
